main.py
app_cmd/__init__.py
app_cmd/buy.py
app_cmd/ticker.py
bilitickerbuy-2.14.10.dist-info/licenses/LICENSE
tab/__init__.py
tab/go.py
tab/log.py
tab/problems.py
tab/settings.py
task/__init__.py
task/buy.py
task/endpoint.py
util/AudioUtil.py
util/BarkUtil.py
util/BiliRequest.py
util/CTokenUtil.py
util/CookieManager.py
util/KVDatabase.py
util/LogConfig.py
util/Notifier.py
util/NtfyUtil.py
util/ProxyTester.py
util/PushPlusUtil.py
util/RandomMessages.py
util/ServerChanUtil.py
util/TimeUtil.py
util/TokenUtil.py
util/__init__.py
bilitickerbuy-2.14.10.dist-info/METADATA
bilitickerbuy-2.14.10.dist-info/WHEEL
bilitickerbuy-2.14.10.dist-info/entry_points.txt
bilitickerbuy-2.14.10.dist-info/top_level.txt
bilitickerbuy-2.14.10.dist-info/RECORD
