Metadata-Version: 2.4
Name: bilitickerbuy
Version: 2.14.10
Summary: 开源的 B 站会员购辅助工具，提供命令行和 Gradio 界面
Author: biliTickerBuy Maintainers
License: MIT License
Project-URL: Homepage, https://github.com/mikumifa/biliTickerBuy
Project-URL: Source, https://github.com/mikumifa/biliTickerBuy
Project-URL: Issues, https://github.com/mikumifa/biliTickerBuy/issues
Keywords: bilibili,tickets,cli,gradio,automation
Classifier: Development Status :: 4 - Beta
Classifier: Intended Audience :: End Users/Desktop
Classifier: License :: OSI Approved :: MIT License
Classifier: Programming Language :: Python :: 3
Classifier: Programming Language :: Python :: 3 :: Only
Classifier: Programming Language :: Python :: 3.11
Classifier: Environment :: Console
Classifier: Environment :: Web Environment
Requires-Python: >=3.11
License-File: LICENSE
Requires-Dist: gradio~=4.44.1
Requires-Dist: gradio-calendar~=0.0.6
Requires-Dist: gradio-log~=0.0.4
Requires-Dist: httpx[socks]>=0.28.1
Requires-Dist: loguru~=0.7.2
Requires-Dist: ntplib~=0.4.0
Requires-Dist: numpy~=1.26.4
Requires-Dist: playsound3~=3.2.2
Requires-Dist: pydantic~=2.8.2
Requires-Dist: qrcode>=7.4.2
Requires-Dist: requests[socks]~=2.31.0
Requires-Dist: retry~=0.9.2
Requires-Dist: setuptools~=65.5.1
Requires-Dist: tinydb~=4.8.0
Requires-Dist: Pillow~=10.3.0
Requires-Dist: huggingface-hub==0.34.3
Dynamic: license-file
